sightengine/__init__.py
sightengine/client.py
sightengine/models.py
sightengine/video_models.py
sightengine_async-0.2.0.dist-info/METADATA
sightengine_async-0.2.0.dist-info/WHEEL
sightengine_async-0.2.0.dist-info/RECORD
