Metadata-Version: 2.3
Name: sightengine-async
Version: 0.2.0
Summary: Asynchronous Python client for the SightEngine API
License: MIT
Keywords: sightengine,async,aiohttp,api
Author: Nate Shoffner
Author-email: nate.shoffner@gmail.com
Requires-Python: >=3.10,<4.0
Classifier: License :: OSI Approved :: MIT License
Classifier: Operating System :: OS Independent
Classifier: Programming Language :: Python :: 3
Classifier: Programming Language :: Python :: 3.10
Classifier: Programming Language :: Python :: 3.11
Classifier: Programming Language :: Python :: 3.12
Classifier: Programming Language :: Python :: 3.13
Requires-Dist: aiohttp (>=3.11.11,<4.0.0)
Requires-Dist: pydantic (>=2.10.4,<3.0.0)
Requires-Dist: python-dotenv (>=1.1.1,<2.0.0)
Project-URL: Bug Tracker, https://github.com/NateShoffner/sightengine-python-async/issues
Project-URL: Homepage, https://github.com/NateShoffner/sightengine-python-async
